<?xml version="1.0" encoding="UTF-8"?>

<CHAT xmlns:xsi="http://www.w3.org/2001/XMLSchema-instance"
      xmlns="http://www.talkbank.org/ns/talkbank"
      xsi:schemaLocation="http://www.talkbank.org/ns/talkbank https://talkbank.org/software/talkbank.xsd"
      Media="e2bt11m221" Mediatypes="audio"
            DesignType="cross"
            ActivityType="tests"
            GroupType="TD"
      PID="11312/c-00014436-1"
      Version="2.20.0"
      Lang="eng"
      Corpus="PaidoEnglish"
      Date="1984-01-01"
      >
  <Participants>
    <participant
      id="CHI"
      role="Target_Child"
      language="eng"
      age="P2Y09M"
      sex="male"

      birthday="1981-04-01"

    />
  </Participants>
  <comment type="Date">01-JAN-1984</comment>
  <comment type="Types">cross, tests, TD</comment>
  <u who="CHI" uID="u0">
    <w>cone</w>
    <t type="p"></t>
    <media
      start="31.207"
      end="32.647"
      unit="s"
    />
    <a type="extension" flavor="wb">kʰon (000:31.207-000:32.647)</a>
    <a type="extension" flavor="wbs">kʰ (000:31.495-000:31.783) O (000:31.783-000:32.071) n (000:32.071-000:32.359)</a>
    <a type="extension" flavor="tr">1 (000:31.471-000:31.620) 1 (000:31.620-000:32.540)</a>
  </u>
  <u who="CHI" uID="u1">
    <w>cocoa</w>
    <t type="p"></t>
    <media
      start="50.414"
      end="51.861"
      unit="s"
    />
    <a type="extension" flavor="wb">kʰo .ko (000:50.414-000:51.861)</a>
    <a type="extension" flavor="wbs">kʰ (000:50.703-000:50.992) O (000:50.992-000:51.282) ko (000:51.282-000:51.571)</a>
    <a type="extension" flavor="tr">1 (000:50.644-000:50.717) 1 (000:50.717-000:50.853)</a>
  </u>
  <u who="CHI" uID="u2">
    <w>donut</w>
    <t type="p"></t>
    <media
      start="60.279"
      end="61.698"
      unit="s"
    />
    <a type="extension" flavor="wb">do .nət (001:00.279-001:01.698)</a>
    <a type="extension" flavor="wbs">d (001:00.563-001:00.847) O (001:00.847-001:01.131) nət (001:01.131-001:01.414)</a>
    <a type="extension" flavor="tr"># (001:00.279-001:00.597) 0 (001:00.597-001:00.681) 0 (001:00.681-001:00.883) $u:o (001:00.883-001:01.414)</a>
  </u>
  <u who="CHI" uID="u3">
    <w>sheep</w>
    <t type="p"></t>
    <media
      start="71.196"
      end="73.246"
      unit="s"
    />
    <a type="extension" flavor="wb">ʃip (001:11.196-001:13.246)</a>
    <a type="extension" flavor="wbs">ʃ (001:11.606-001:12.016) I (001:12.016-001:12.426) p (001:12.426-001:12.836)</a>
    <a type="extension" flavor="tr">E (001:11.993-001:12.215) 0 (001:12.215-001:12.811) $e:i (001:12.811-001:13.116) nonInitial (001:13.116-001:13.246)</a>
  </u>
  <u who="CHI" uID="u4">
    <w>chute</w>
    <t type="p"></t>
    <media
      start="76.664"
      end="78.465"
      unit="s"
    />
    <a type="extension" flavor="wb">ʃut (001:16.664-001:18.465)</a>
    <a type="extension" flavor="wbs">ʃ (001:17.024-001:17.384) U (001:17.384-001:17.745) t (001:17.745-001:18.105)</a>
    <a type="extension" flavor="tr">1 (001:17.041-001:17.262) 1 (001:17.262-001:17.887) nonInitial (001:18.105-001:18.465)</a>
  </u>
  <u who="CHI" uID="u5">
    <w>cake</w>
    <t type="p"></t>
    <media
      start="92.736"
      end="94.332"
      unit="s"
    />
    <a type="extension" flavor="wb">kʰek (001:32.736-001:34.332)</a>
    <a type="extension" flavor="wbs">kʰ (001:33.055-001:33.374) E (001:33.374-001:33.693) k (001:33.693-001:34.013)</a>
    <a type="extension" flavor="tr">1 (001:33.323-001:33.430) 1 (001:33.430-001:33.866) nonInitial (001:34.013-001:34.332)</a>
  </u>
  <u who="CHI" uID="u6">
    <w>gift</w>
    <t type="p"></t>
    <media
      start="106.190"
      end="107.273"
      unit="s"
    />
    <a type="extension" flavor="wb">gɪft (001:46.190-001:47.273)</a>
    <a type="extension" flavor="wbs">g (001:46.407-001:46.623) I (001:46.623-001:46.840) ft (001:46.840-001:47.057)</a>
    <a type="extension" flavor="tr">1 (001:46.479-001:46.512) 0 (001:46.512-001:46.789) $@ (001:46.789-001:47.057)</a>
  </u>
  <u who="CHI" uID="u7">
    <w>tepee</w>
    <t type="p"></t>
    <media
      start="118.814"
      end="120.409"
      unit="s"
    />
    <a type="extension" flavor="wb">tʰi .pi (001:58.814-002:00.409)</a>
    <a type="extension" flavor="wbs">tʰ (001:59.133-001:59.452) I (001:59.452-001:59.771) pi (001:59.771-002:00.090)</a>
  </u>
  <u who="CHI" uID="u8">
    <w>chores</w>
    <t type="p"></t>
    <media
      start="130.267"
      end="131.485"
      unit="s"
    />
    <a type="extension" flavor="wb">tʃʰoɹz (002:10.267-002:11.485)</a>
    <a type="extension" flavor="wbs">overlap (002:10.267-002:10.511) tʃʰ (002:10.511-002:10.754) O (002:10.754-002:10.998) ɹz (002:10.998-002:11.241)</a>
    <a type="extension" flavor="tr">m (002:10.511-002:10.754) m (002:10.754-002:10.998)</a>
  </u>
  <u who="CHI" uID="u9">
    <w>door</w>
    <t type="p"></t>
    <media
      start="145.117"
      end="146.717"
      unit="s"
    />
    <a type="extension" flavor="wb">doɹ (002:25.117-002:26.717)</a>
    <a type="extension" flavor="wbs">d (002:25.437-002:25.757) O (002:25.757-002:26.077) ɹ (002:26.077-002:26.397)</a>
    <a type="extension" flavor="tr">1 (002:25.544-002:25.556) 1 (002:25.556-002:26.035)</a>
  </u>
  <u who="CHI" uID="u10">
    <w>kicking</w>
    <t type="p"></t>
    <media
      start="149.075"
      end="150.819"
      unit="s"
    />
    <a type="extension" flavor="wb">kʰɪ .kɪxŋ (002:29.075-002:30.819)</a>
    <a type="extension" flavor="wbs">kʰ (002:29.424-002:29.772) I (002:29.772-002:30.121) kIxŋ (002:30.121-002:30.470)</a>
    <a type="extension" flavor="tr">1 (002:29.343-002:29.439) 1 (002:29.439-002:29.631)</a>
  </u>
  <u who="CHI" uID="u11">
    <w>seashore</w>
    <t type="p"></t>
    <media
      start="153.852"
      end="155.900"
      unit="s"
    />
    <a type="extension" flavor="wb">si .ʃoɹ (002:33.852-002:35.900)</a>
    <a type="extension" flavor="wbs">s (002:34.262-002:34.671) I (002:34.671-002:35.081) ʃoɹ (002:35.081-002:35.491)</a>
    <a type="extension" flavor="tr">1 (002:34.176-002:34.266) 1 (002:34.266-002:34.469) nonInitial (002:35.491-002:35.900)</a>
  </u>
  <u who="CHI" uID="u12">
    <w>cutting</w>
    <t type="p"></t>
    <media
      start="163.244"
      end="165.114"
      unit="s"
    />
    <a type="extension" flavor="wb">kʰʌ .tɪxŋ (002:43.244-002:45.114)</a>
    <a type="extension" flavor="wbs">kʰ (002:43.618-002:43.992) A (002:43.992-002:44.366) tIxŋ (002:44.366-002:44.740)</a>
    <a type="extension" flavor="tr">1 (002:43.683-002:43.733) 1 (002:43.733-002:43.966)</a>
  </u>
  <u who="CHI" uID="u13">
    <w>sister</w>
    <t type="p"></t>
    <media
      start="168.056"
      end="169.714"
      unit="s"
    />
    <a type="extension" flavor="wb">sɪs .tər (002:48.056-002:49.714)</a>
    <a type="extension" flavor="wbs">s (002:48.388-002:48.720) I (002:48.720-002:49.051) stər (002:49.051-002:49.383)</a>
    <a type="extension" flavor="tr">s:$T (002:48.056-002:48.483) 1 (002:48.483-002:48.649) 1 (002:48.649-002:48.882) nonInitial (002:49.383-002:49.714)</a>
  </u>
  <u who="CHI" uID="u14">
    <w>chewing</w>
    <t type="p"></t>
    <media
      start="178.299"
      end="180.100"
      unit="s"
    />
    <a type="extension" flavor="wb">tʃʰu .ɪxŋ (002:58.299-003:00.100)</a>
    <a type="extension" flavor="wbs">ðɸ (002:58.299-002:58.659) tʃʰ (002:58.659-002:59.019) U (002:59.019-002:59.379) Iŋ (002:59.379-002:59.740)</a>
    <a type="extension" flavor="tr">$th:tSh (002:58.299-002:59.012) 0 (002:59.012-002:59.083) 1 (002:59.083-002:59.309) nonInitial (002:59.740-003:00.100)</a>
  </u>
  <u who="CHI" uID="u15">
    <w>dolphin</w>
    <t type="p"></t>
    <media
      start="191.325"
      end="192.991"
      unit="s"
    />
    <a type="extension" flavor="wb">dɑl .fɪxn (003:11.325-003:12.991)</a>
    <a type="extension" flavor="wbs">d (003:11.658-003:11.991) A (003:11.991-003:12.324) fIxn (003:12.324-003:12.658)</a>
    <a type="extension" flavor="tr">+nd (003:11.325-003:11.710) 0 (003:11.710-003:11.793) 1 (003:11.793-003:11.958)</a>
  </u>
  <u who="CHI" uID="u16">
    <w>chosen</w>
    <t type="p"></t>
    <media
      start="198.222"
      end="199.750"
      unit="s"
    />
    <a type="extension" flavor="wb">tʃʰo .zən (003:18.222-003:19.750)</a>
    <a type="extension" flavor="wbs">tʃʰ (003:18.527-003:18.833) O (003:18.833-003:19.139) zən (003:19.139-003:19.445)</a>
    <a type="extension" flavor="tr">1 (003:18.627-003:18.781) 0 (003:18.781-003:18.994) $u (003:18.994-003:19.445) nonInitial (003:19.445-003:19.750)</a>
  </u>
  <u who="CHI" uID="u17">
    <w>color</w>
    <t type="p"></t>
    <media
      start="204.711"
      end="205.953"
      unit="s"
    />
    <a type="extension" flavor="wb">kʰʌ .lər (003:24.711-003:25.953)</a>
    <a type="extension" flavor="wbs">kʰ (003:24.959-003:25.208) A (003:25.208-003:25.456) lər (003:25.456-003:25.704)</a>
    <a type="extension" flavor="tr">1 (003:25.025-003:25.078) 1 (003:25.078-003:25.322)</a>
  </u>
  <u who="CHI" uID="u18">
    <w>gumdrops</w>
    <t type="p"></t>
    <media
      start="209.414"
      end="210.702"
      unit="s"
    />
    <a type="extension" flavor="wb">gʌm .dɹɑps (003:29.414-003:30.702)</a>
    <a type="extension" flavor="wbs">g (003:29.672-003:29.929) A (003:29.929-003:30.187) m .dɹAps (003:30.187-003:30.444)</a>
    <a type="extension" flavor="tr">$d:g (003:29.414-003:29.681) 0 (003:29.681-003:29.702) 1 (003:29.702-003:29.783)</a>
  </u>
  <u who="CHI" uID="u19">
    <w>sodas</w>
    <t type="p"></t>
    <media
      start="219.928"
      end="221.280"
      unit="s"
    />
    <a type="extension" flavor="wb">so .dəz (003:39.928-003:41.280)</a>
    <a type="extension" flavor="wbs">ðɸ (003:39.928-003:40.198) s (003:40.198-003:40.469) O (003:40.469-003:40.739) dəz (003:40.739-003:41.010)</a>
    <a type="extension" flavor="tr">+tjh (003:39.928-003:40.241) 0 (003:40.241-003:40.280) 1 (003:40.280-003:40.478) o:$u (003:40.478-003:41.010)</a>
  </u>
  <u who="CHI" uID="u20">
    <w>tweezers</w>
    <t type="p"></t>
    <media
      start="225.213"
      end="226.802"
      unit="s"
    />
    <a type="extension" flavor="wb">tʷʰhi .zərz (003:45.213-003:46.802)</a>
    <a type="extension" flavor="wbs">tʷʰh (003:45.531-003:45.848) I (003:45.848-003:46.166) zərz (003:46.166-003:46.484)</a>
    <a type="extension" flavor="tr">$th:$tSh (003:45.213-003:45.470) 0 (003:45.470-003:45.554) 0 (003:45.554-003:45.927) $e (003:45.927-003:46.484) nonInitial (003:46.484-003:46.802)</a>
  </u>
  <u who="CHI" uID="u21">
    <w>dude</w>
    <t type="p"></t>
    <media
      start="260.160"
      end="261.762"
      unit="s"
    />
    <a type="extension" flavor="wb">dud (004:20.160-004:21.762)</a>
    <a type="extension" flavor="wbs">d (004:20.481-004:20.801) U (004:20.801-004:21.121) d (004:21.121-004:21.442)</a>
    <a type="extension" flavor="tr">d:# (004:20.160-004:20.613) 1 (004:20.613-004:20.638) 1 (004:20.638-004:21.495)</a>
  </u>
  <u who="CHI" uID="u22">
    <w>chimney</w>
    <t type="p"></t>
    <media
      start="270.785"
      end="272.106"
      unit="s"
    />
    <a type="extension" flavor="wb">tʃʰɪm .ni (004:30.785-004:32.106)</a>
    <a type="extension" flavor="wbs">tʃʰ (004:31.049-004:31.313) I (004:31.313-004:31.578) m .ni (004:31.578-004:31.842)</a>
    <a type="extension" flavor="tr">#:+hz (004:30.785-004:31.026) 0 (004:31.026-004:31.217) 0 (004:31.217-004:31.468) $A (004:31.468-004:31.842)</a>
  </u>
  <u who="CHI" uID="u23">
    <w>cookie</w>
    <t type="p"></t>
    <media
      start="277.428"
      end="278.716"
      unit="s"
    />
    <a type="extension" flavor="wb">kʰʊ .ki (004:37.428-004:38.716)</a>
    <a type="extension" flavor="wbs">kʰ (004:37.686-004:37.943) U (004:37.943-004:38.201) ki (004:38.201-004:38.458)</a>
    <a type="extension" flavor="tr">1 (004:37.928-004:38.003) 1 (004:38.003-004:38.179) nonInitial (004:38.458-004:38.716)</a>
  </u>
  <u who="CHI" uID="u24">
    <w>cube</w>
    <t type="p"></t>
    <media
      start="296.561"
      end="298.198"
      unit="s"
    />
    <a type="extension" flavor="wb">kʲʰub (004:56.561-004:58.198)</a>
    <a type="extension" flavor="wbs">kʲʰ (004:56.888-004:57.216) U (004:57.216-004:57.543) b (004:57.543-004:57.871)</a>
    <a type="extension" flavor="tr">$khij (004:56.561-004:57.201) 0 (004:57.201-004:57.612) 1 (004:57.612-004:57.864) nonInitial_insertion (004:57.999-004:58.198)</a>
  </u>
  <u who="CHI" uID="u25">
    <w>toast</w>
    <t type="p"></t>
    <media
      start="300.291"
      end="301.722"
      unit="s"
    />
    <a type="extension" flavor="wb">tʰost (005:00.291-005:01.722)</a>
    <a type="extension" flavor="wbs">tʰ (005:00.577-005:00.863) O (005:00.863-005:01.150) st (005:01.150-005:01.436)</a>
    <a type="extension" flavor="tr">1 (005:00.697-005:00.829) 1 (005:00.829-005:01.243)</a>
  </u>
  <u who="CHI" uID="u26">
    <w>chess</w>
    <t type="p"></t>
    <media
      start="304.739"
      end="305.593"
      unit="s"
    />
    <a type="extension" flavor="wb">tʃʰɛs (005:04.739-005:05.593)</a>
    <a type="extension" flavor="wbs">overlap (005:04.739-005:04.910) tʃʰ (005:04.910-005:05.080) E (005:05.080-005:05.251) s (005:05.251-005:05.422)</a>
    <a type="extension" flavor="tr">m (005:04.866-005:04.935) m (005:04.935-005:05.303)</a>
  </u>
  <u who="CHI" uID="u27">
    <w>toast</w>
    <t type="p"></t>
    <media
      start="305.970"
      end="307.163"
      unit="s"
    />
    <a type="extension" flavor="wb">tʰost (005:05.970-005:07.163)</a>
    <a type="extension" flavor="wbs">tʰ (005:06.208-005:06.447) O (005:06.447-005:06.686) st (005:06.686-005:06.924)</a>
    <a type="extension" flavor="tr">$tSh (005:05.970-005:06.207) 0 (005:06.207-005:06.277) 1 (005:06.277-005:06.742) nonInitial (005:06.924-005:07.163)</a>
  </u>
  <u who="CHI" uID="u28">
    <w>shark</w>
    <t type="p"></t>
    <media
      start="314.798"
      end="316.649"
      unit="s"
    />
    <a type="extension" flavor="wb">ʃɑɹk (005:14.798-005:16.649)</a>
    <a type="extension" flavor="wbs">ʃ (005:15.168-005:15.538) A (005:15.538-005:15.908) ɹk (005:15.908-005:16.279)</a>
    <a type="extension" flavor="tr">S:$s (005:14.798-005:15.454) 1 (005:15.454-005:15.624) 0 (005:15.624-005:15.994) $o (005:15.994-005:16.279)</a>
  </u>
  <u who="CHI" uID="u29">
    <w>tube</w>
    <t type="p"></t>
    <media
      start="319.236"
      end="320.509"
      unit="s"
    />
    <a type="extension" flavor="wb">tʰub (005:19.236-005:20.509)</a>
    <a type="extension" flavor="wbs">tʰ (005:19.490-005:19.745) U (005:19.745-005:20.000) b (005:20.000-005:20.254)</a>
    <a type="extension" flavor="tr">$tSh:th (005:19.236-005:19.503) 0 (005:19.503-005:19.680) 1 (005:19.680-005:20.010)</a>
  </u>
  <u who="CHI" uID="u30">
    <w>tube</w>
    <t type="p"></t>
    <media
      start="321.906"
      end="322.989"
      unit="s"
    />
    <a type="extension" flavor="wb">tʰub (005:21.906-005:22.989)</a>
    <a type="extension" flavor="wbs">tʰ (005:22.401-005:22.579) U (005:22.579-005:22.692) b (005:22.692-005:22.857)</a>
  </u>
  <u who="CHI" uID="u31">
    <w>deer</w>
    <t type="p"></t>
    <media
      start="323.048"
      end="324.510"
      unit="s"
    />
    <a type="extension" flavor="wb">diɹ (005:23.048-005:24.510)</a>
    <a type="extension" flavor="wbs">d (005:23.341-005:23.633) I (005:23.633-005:23.925) ɹ (005:23.925-005:24.217)</a>
  </u>
  <u who="CHI" uID="u32">
    <w>deer</w>
    <t type="p"></t>
    <media
      start="328.993"
      end="330.034"
      unit="s"
    />
    <a type="extension" flavor="wb">diɹ (005:28.993-005:30.034)</a>
    <a type="extension" flavor="wbs">d (005:29.201-005:29.410) I (005:29.410-005:29.618) ɹ (005:29.618-005:29.826)</a>
    <a type="extension" flavor="tr">d:$th (005:28.993-005:29.249) 1 (005:29.249-005:29.296) 1 (005:29.296-005:29.604)</a>
  </u>
  <u who="CHI" uID="u33">
    <w>kitchen</w>
    <t type="p"></t>
    <media
      start="336.330"
      end="338.096"
      unit="s"
    />
    <a type="extension" flavor="wb">kʰɪ .tʃɪxn (005:36.330-005:38.096)</a>
    <a type="extension" flavor="wbs">kʰ (005:36.683-005:37.036) I (005:37.036-005:37.389) tʃIxn (005:37.389-005:37.743)</a>
    <a type="extension" flavor="tr">$g (005:36.330-005:36.707) V (005:36.707-005:36.740) 1 (005:36.740-005:36.977)</a>
  </u>
  <u who="CHI" uID="u34">
    <w>soccer</w>
    <t type="p"></t>
    <media
      start="344.103"
      end="345.290"
      unit="s"
    />
    <a type="extension" flavor="wb">sɑ .kər (005:44.103-005:45.290)</a>
    <a type="extension" flavor="wbs">s (005:44.340-005:44.577) A (005:44.577-005:44.815) kər (005:44.815-005:45.052)</a>
    <a type="extension" flavor="tr">$S (005:44.103-005:44.211) 0 (005:44.211-005:44.365) 1 (005:44.365-005:44.600) aU (005:44.600-005:45.052)</a>
  </u>
  <u who="CHI" uID="u35">
    <w>super</w>
    <t type="p"></t>
    <media
      start="349.233"
      end="350.450"
      unit="s"
    />
    <a type="extension" flavor="wb">su .pər (005:49.233-005:50.450)</a>
    <a type="extension" flavor="wbs">s (005:49.476-005:49.720) U (005:49.720-005:49.963) pər (005:49.963-005:50.207)</a>
    <a type="extension" flavor="tr">$Z:$dZ (005:49.233-005:49.388) 0 (005:49.388-005:49.443) 1 (005:49.443-005:49.642)</a>
  </u>
  <u who="CHI" uID="u36">
    <w>desert</w>
    <t type="p"></t>
    <media
      start="353.661"
      end="354.822"
      unit="s"
    />
    <a type="extension" flavor="wb">dɛ .zərt (005:53.661-005:54.822)</a>
    <a type="extension" flavor="wbs">d (005:53.893-005:54.125) E (005:54.125-005:54.358) zərt (005:54.358-005:54.590)</a>
    <a type="extension" flavor="tr">$h (005:53.661-005:53.769) 0 (005:53.769-005:53.830) 1 (005:53.830-005:54.029)</a>
  </u>
  <u who="CHI" uID="u37">
    <w>tongue</w>
    <t type="p"></t>
    <media
      start="357.600"
      end="359.098"
      unit="s"
    />
    <a type="extension" flavor="wb">tʰʌŋ (005:57.600-005:59.098)</a>
    <a type="extension" flavor="wbs">tʰ (005:57.900-005:58.199) A (005:58.199-005:58.499) ŋ (005:58.499-005:58.799)</a>
    <a type="extension" flavor="tr">1 (005:57.953-005:58.017) 1 (005:58.017-005:58.704)</a>
  </u>
  <u who="CHI" uID="u38">
    <w>checkers</w>
    <t type="p"></t>
    <media
      start="368.367"
      end="370.123"
      unit="s"
    />
    <a type="extension" flavor="wb">tʃʰɛk .ərz (006:08.367-006:10.123)</a>
    <a type="extension" flavor="wbs">tʃʰ (006:08.718-006:09.069) E (006:09.069-006:09.421) k .ərz (006:09.421-006:09.772)</a>
    <a type="extension" flavor="tr">$s (006:08.367-006:08.747) 0 (006:08.747-006:08.932) 1 (006:08.932-006:09.143) nonInitial (006:09.772-006:10.123)</a>
  </u>
  <u who="CHI" uID="u39">
    <w>suitcase</w>
    <t type="p"></t>
    <media
      start="378.882"
      end="380.363"
      unit="s"
    />
    <a type="extension" flavor="wb">sut .kes (006:18.882-006:20.363)</a>
    <a type="extension" flavor="wbs">s (006:19.178-006:19.474) U (006:19.474-006:19.770) t .kes (006:19.770-006:20.067)</a>
    <a type="extension" flavor="tr">#:$th (006:18.882-006:19.016) 0 (006:19.016-006:19.117) 1 (006:19.117-006:19.291)</a>
  </u>
  <u who="CHI" uID="u40">
    <w>same</w>
    <t type="p"></t>
    <media
      start="389.701"
      end="391.295"
      unit="s"
    />
    <a type="extension" flavor="wb">sem (006:29.701-006:31.295)</a>
    <a type="extension" flavor="wbs">s (006:30.020-006:30.339) E (006:30.339-006:30.657) m (006:30.657-006:30.976)</a>
    <a type="extension" flavor="tr">+kCSh (006:29.701-006:30.183) 0 (006:30.183-006:30.397) 1 (006:30.397-006:30.924)</a>
  </u>
  <u who="CHI" uID="u41">
    <w>quake</w>
    <t type="p"></t>
    <media
      start="399.699"
      end="401.402"
      unit="s"
    />
    <a type="extension" flavor="wb">kʷʰek (006:39.699-006:41.402)</a>
    <a type="extension" flavor="wbs">kʷʰ (006:40.039-006:40.380) E (006:40.380-006:40.721) k (006:40.721-006:41.062)</a>
    <a type="extension" flavor="tr">$kh (006:39.699-006:40.164) 0 (006:40.164-006:40.283) 1 (006:40.283-006:41.088) nonInitial (006:41.261-006:41.402)</a>
  </u>
  <u who="CHI" uID="u42">
    <w>chalkboard</w>
    <t type="p"></t>
    <media
      start="419.515"
      end="421.491"
      unit="s"
    />
    <a type="extension" flavor="wb">tʃʰɑk .boɹd (006:59.515-007:01.491)</a>
    <a type="extension" flavor="wbs">tʃʰ (006:59.910-007:00.305) A (007:00.305-007:00.701) k .boɹd (007:00.701-007:01.096)</a>
    <a type="extension" flavor="tr">$d (006:59.515-006:59.807) 0 (006:59.807-006:59.830) 1 (006:59.830-006:59.975)</a>
  </u>
  <u who="CHI" uID="u43">
    <w>quick</w>
    <t type="p"></t>
    <media
      start="422.598"
      end="424.371"
      unit="s"
    />
    <a type="extension" flavor="wb">kʷʰɪk (007:02.598-007:04.371)</a>
    <a type="extension" flavor="wbs">kʷʰ (007:02.952-007:03.307) I (007:03.307-007:03.662) k (007:03.662-007:04.017)</a>
  </u>
  <u who="CHI" uID="u44">
    <w>quick</w>
    <t type="p"></t>
    <media
      start="430.587"
      end="432.139"
      unit="s"
    />
    <a type="extension" flavor="wb">kʷʰɪk (007:10.587-007:12.139)</a>
    <a type="extension" flavor="wbs">kʷʰ (007:10.897-007:11.208) I (007:11.208-007:11.518) k (007:11.518-007:11.829)</a>
    <a type="extension" flavor="tr">1 (007:10.837-007:11.124) 1 (007:11.124-007:11.685) E:$@ (007:11.685-007:11.829)</a>
  </u>
  <u who="CHI" uID="u45">
    <w>tail</w>
    <t type="p"></t>
    <media
      start="438.278"
      end="439.290"
      unit="s"
    />
    <a type="extension" flavor="wb">tʰe .əl (007:18.278-007:19.290)</a>
    <a type="extension" flavor="wbs">overlap (007:18.278-007:18.480) tʰ (007:18.480-007:18.683) E (007:18.683-007:18.885) əl (007:18.885-007:19.087)</a>
  </u>
  <u who="CHI" uID="u46">
    <w>tail</w>
    <t type="p"></t>
    <media
      start="439.342"
      end="440.982"
      unit="s"
    />
    <a type="extension" flavor="wb">tʰe .əl (007:19.342-007:20.982)</a>
    <a type="extension" flavor="wbs">tʰ (007:19.670-007:19.998) E (007:19.998-007:20.326) əl (007:20.326-007:20.654)</a>
  </u>
  <u who="CHI" uID="u47">
    <w>tail</w>
    <t type="p"></t>
    <media
      start="441.048"
      end="442.126"
      unit="s"
    />
    <a type="extension" flavor="wb">tʰe .əl (007:21.048-007:22.126)</a>
    <a type="extension" flavor="wbs">tʰ (007:21.264-007:21.479) E (007:21.479-007:21.695) əl (007:21.695-007:21.911)</a>
    <a type="extension" flavor="tr">1 (007:21.321-007:21.444) 1 (007:21.444-007:21.873) nonInitial (007:22.057-007:22.126)</a>
  </u>
  <u who="CHI" uID="u48">
    <w>golf</w>
    <t type="p"></t>
    <media
      start="453.198"
      end="454.803"
      unit="s"
    />
    <a type="extension" flavor="wb">gɑlf (007:33.198-007:34.803)</a>
    <a type="extension" flavor="wbs">g (007:33.519-007:33.840) A (007:33.840-007:34.161) lf (007:34.161-007:34.482)</a>
    <a type="extension" flavor="tr">1 (007:33.594-007:33.609) 1 (007:33.609-007:34.221)</a>
  </u>
  <u who="CHI" uID="u49">
    <w>torn</w>
    <t type="p"></t>
    <media
      start="462.978"
      end="464.492"
      unit="s"
    />
    <a type="extension" flavor="wb">tʰoɹn (007:42.978-007:44.492)</a>
    <a type="extension" flavor="wbs">tʰ (007:43.281-007:43.584) O (007:43.584-007:43.886) ɹn (007:43.886-007:44.189)</a>
    <a type="extension" flavor="tr">1 (007:43.360-007:43.490) 1 (007:43.490-007:43.936)</a>
  </u>
  <u who="CHI" uID="u50">
    <w>shape</w>
    <t type="p"></t>
    <media
      start="471.824"
      end="473.374"
      unit="s"
    />
    <a type="extension" flavor="wb">ʃep (007:51.824-007:53.374)</a>
    <a type="extension" flavor="wbs">ʃ (007:52.134-007:52.444) E (007:52.444-007:52.754) p (007:52.754-007:53.064)</a>
    <a type="extension" flavor="tr">1 (007:52.061-007:52.240) 0 (007:52.240-007:52.935) $Ie (007:52.935-007:53.064)</a>
  </u>
  <u who="CHI" uID="u51">
    <w>thimble</w>
    <t type="p"></t>
    <media
      start="490.669"
      end="492.072"
      unit="s"
    />
    <a type="extension" flavor="wb">θɪm .bəl (008:10.669-008:12.072)</a>
    <a type="extension" flavor="wbs">θ (008:10.950-008:11.231) I (008:11.231-008:11.511) m .bəl (008:11.511-008:11.792)</a>
    <a type="extension" flavor="tr">$s (008:10.669-008:10.931) 0 (008:10.931-008:11.059) 0 (008:11.059-008:11.313) # (008:11.313-008:11.792)</a>
  </u>
  <u who="CHI" uID="u52">
    <w>thimble</w>
    <t type="p"></t>
    <media
      start="494.750"
      end="495.951"
      unit="s"
    />
    <a type="extension" flavor="wb">θɪm .bəl (008:14.750-008:15.951)</a>
    <a type="extension" flavor="wbs">θ (008:14.990-008:15.230) I (008:15.230-008:15.471) m .bəl (008:15.471-008:15.711)</a>
  </u>
  <u who="CHI" uID="u53">
    <w>sun</w>
    <t type="p"></t>
    <media
      start="500.339"
      end="501.675"
      unit="s"
    />
    <a type="extension" flavor="wb">sʌn (008:20.339-008:21.675)</a>
    <a type="extension" flavor="wbs">ðɸ (008:20.339-008:20.606) s (008:20.606-008:20.873) A (008:20.873-008:21.140) n (008:21.140-008:21.408)</a>
    <a type="extension" flavor="tr">$T (008:20.339-008:20.602) 0 (008:20.602-008:20.691) 1 (008:20.691-008:21.279) nonInitial (008:21.597-008:21.675)</a>
  </u>
  <u who="CHI" uID="u54">
    <w>tickle</w>
    <t type="p"></t>
    <media
      start="509.078"
      end="511.488"
      unit="s"
    />
    <a type="extension" flavor="wb">tʰɪ .kəl (008:29.078-008:31.488)</a>
    <a type="extension" flavor="wbs">tʰ (008:29.560-008:30.042) I (008:30.042-008:30.524) kəl (008:30.524-008:31.006)</a>
    <a type="extension" flavor="tr"># (008:29.078-008:30.145) 0 (008:30.145-008:30.414) 1 (008:30.414-008:30.644)</a>
  </u>
  <u who="CHI" uID="u55">
    <w>question</w>
    <t type="p"></t>
    <media
      start="516.314"
      end="518.256"
      unit="s"
    />
    <a type="extension" flavor="wb">kʷʰɛs .tʃən (008:36.314-008:38.256)</a>
    <a type="extension" flavor="wbs">kʷʰ (008:36.702-008:37.091) E (008:37.091-008:37.479) s .tʃən (008:37.479-008:37.867)</a>
    <a type="extension" flavor="tr">$g (008:36.314-008:36.907) 0 (008:36.907-008:36.937) 1 (008:36.937-008:37.179) E:$@ (008:37.179-008:37.867)</a>
  </u>
  <u who="CHI" uID="u56">
    <w>tuna</w>
    <t type="p"></t>
    <media
      start="522.827"
      end="524.145"
      unit="s"
    />
    <a type="extension" flavor="wb">tʰu .nə (008:42.827-008:44.145)</a>
    <a type="extension" flavor="wbs">tʰ (008:43.091-008:43.354) U (008:43.354-008:43.618) nə (008:43.618-008:43.881)</a>
    <a type="extension" flavor="tr">1 (008:43.116-008:43.193) 1 (008:43.193-008:43.437)</a>
  </u>
  <u who="CHI" uID="u57">
    <w>soldier</w>
    <t type="p"></t>
    <media
      start="527.877"
      end="529.156"
      unit="s"
    />
    <a type="extension" flavor="wb">sol .dʒər (008:47.877-008:49.156)</a>
    <a type="extension" flavor="wbs">s (008:48.133-008:48.389) O (008:48.389-008:48.644) ldzər (008:48.644-008:48.900)</a>
    <a type="extension" flavor="tr"># (008:47.877-008:48.079) 0 (008:48.079-008:48.238) 1 (008:48.238-008:48.501) nonInitial (008:48.900-008:49.156)</a>
  </u>
  <u who="CHI" uID="u58">
    <w>tall</w>
    <t type="p"></t>
    <media
      start="545.584"
      end="547.051"
      unit="s"
    />
    <a type="extension" flavor="wb">tʰɑl (009:05.584-009:07.051)</a>
    <a type="extension" flavor="wbs">tʰ (009:05.878-009:06.171) A (009:06.171-009:06.464) l (009:06.464-009:06.758)</a>
    <a type="extension" flavor="tr">1 (009:06.023-009:06.140) 0 (009:06.140-009:06.668) $o (009:06.668-009:06.758)</a>
  </u>
  <u who="CHI" uID="u59">
    <w>deck</w>
    <t type="p"></t>
    <media
      start="552.929"
      end="554.230"
      unit="s"
    />
    <a type="extension" flavor="wb">dɛk (009:12.929-009:14.230)</a>
    <a type="extension" flavor="wbs">d (009:13.189-009:13.449) E (009:13.449-009:13.710) k (009:13.710-009:13.970)</a>
  </u>
  <u who="CHI" uID="u60">
    <w>shore</w>
    <t type="p"></t>
    <media
      start="559.481"
      end="560.487"
      unit="s"
    />
    <a type="extension" flavor="wb">ʃor (009:19.481-009:20.487)</a>
    <a type="extension" flavor="wbs">ʃ (009:19.682-009:19.883) O (009:19.883-009:20.084) ɹ (009:20.084-009:20.286)</a>
    <a type="extension" flavor="tr">$tSh:S (009:19.481-009:19.762) 0 (009:19.762-009:19.883) 1 (009:19.883-009:20.133)</a>
  </u>
  <u who="CHI" uID="u61">
    <w>seven</w>
    <t type="p"></t>
    <media
      start="574.648"
      end="576.175"
      unit="s"
    />
    <a type="extension" flavor="wb">sɛ .vɪxn (009:34.648-009:36.175)</a>
    <a type="extension" flavor="wbs">s (009:34.954-009:35.259) E (009:35.259-009:35.565) vIxn (009:35.565-009:35.870)</a>
  </u>
  <u who="CHI" uID="u62">
    <w>seven</w>
    <t type="p"></t>
    <media
      start="601.049"
      end="602.954"
      unit="s"
    />
    <a type="extension" flavor="wb">sɛ .vɪxn (010:01.049-010:02.954)</a>
    <a type="extension" flavor="wbs">ðɸ (010:01.049-010:01.430) s (010:01.430-010:01.811) E (010:01.811-010:02.192) vIxn (010:02.192-010:02.573)</a>
    <a type="extension" flavor="tr">1 (010:01.880-010:02.025) 1 (010:02.025-010:02.291) nonInitial (010:02.573-010:02.954)</a>
  </u>
</CHAT>