<?xml version="1.0" encoding="UTF-8" standalone="yes"?>
<session xmlns="http://phon.ling.mun.ca/ns/phonbank" id="010823" corpus="ComptonPater" version="PB1.2">
    <header>
        <date>1973-09-10</date>
        <language>eng</language>
    </header>
    <participants>
        <participant id="CHI">
            <role>Target Child</role>
            <name>Julia</name>
            <sex>female</sex>
            <age>P1Y8M23DT0H0M0S</age>
            <language>eng</language>
        </participant>
    </participants>
    <transcribers/>
    <userTiers>
        <userTier tierName="uttnum" grouped="false"/>
        <userTier tierName="sesdat" grouped="false"/>
        <userTier tierName="age" grouped="false"/>
    </userTiers>
    <tierOrder>
        <tier tierName="Orthography" visible="true" locked="false" font="default"/>
        <tier tierName="IPA Target" visible="true" locked="false" font="default"/>
        <tier tierName="IPA Actual" visible="true" locked="false" font="default"/>
        <tier tierName="Notes" visible="true" locked="false" font="default"/>
        <tier tierName="Segment" visible="true" locked="false" font="default"/>
        <tier tierName="uttnum" visible="true" locked="false" font="default"/>
        <tier tierName="sesdat" visible="true" locked="false" font="default"/>
        <tier tierName="age" visible="true" locked="false" font="default"/>
    </tierOrder>
    <transcript>
        <comment type="Code">pid 11312/c-00011333-1</comment>
        <comment type="Date">10-SEP-1973</comment>
        <u speaker="CHI" id="130cf83d-2454-4ffd-a498-a7a35857f1d1" excludeFromSearches="false">
            <orthography>
                <g>
                    <w>milk</w>
                    <p type="PERIOD">.</p>
                </g>
            </orthography>
            <ipaTier form="model">
                <pg>
                    <w>ˈmɪlk</w>
                    <sb>
                        <ph indexes="0" scType="SS"/>
                        <ph indexes="1" scType="UK"/>
                        <ph indexes="2" scType="UK"/>
                        <ph indexes="3" scType="UK"/>
                        <ph indexes="4" scType="UK"/>
                    </sb>
                </pg>
            </ipaTier>
            <ipaTier form="actual">
                <pg>
                    <w>mʊk</w>
                    <sb>
                        <ph indexes="0" scType="UK"/>
                        <ph indexes="1" scType="UK"/>
                        <ph indexes="2" scType="UK"/>
                    </sb>
                </pg>
            </ipaTier>
            <alignment type="segmental">
                <ag length="0"/>
            </alignment>
            <segment startTime="0.0" duration="0.0" unitType="ms"/>
            <flatTier tierName="uttnum">1096</flatTier>
            <flatTier tierName="sesdat">1973-09-10</flatTier>
            <flatTier tierName="age">1;8.24</flatTier>
        </u>
        <u speaker="CHI" id="3bb72be0-4a54-413e-93d6-1f26219a46ed" excludeFromSearches="false">
            <orthography>
                <g>
                    <w>blankie</w>
                    <p type="PERIOD">.</p>
                </g>
            </orthography>
            <ipaTier form="model">
                <pg>
                    <w>ˈblæŋkiː</w>
                    <sb>
                        <ph indexes="0" scType="SS"/>
                        <ph indexes="1" scType="UK"/>
                        <ph indexes="2" scType="UK"/>
                        <ph indexes="3" scType="UK"/>
                        <ph indexes="4" scType="UK"/>
                        <ph indexes="5" scType="UK"/>
                        <ph indexes="6 7" scType="UK"/>
                    </sb>
                </pg>
            </ipaTier>
            <ipaTier form="actual">
                <pg>
                    <w>bæŋki</w>
                    <sb>
                        <ph indexes="0" scType="UK"/>
                        <ph indexes="1" scType="UK"/>
                        <ph indexes="2" scType="UK"/>
                        <ph indexes="3" scType="UK"/>
                        <ph indexes="4" scType="UK"/>
                    </sb>
                </pg>
            </ipaTier>
            <alignment type="segmental">
                <ag length="0"/>
            </alignment>
            <segment startTime="0.0" duration="0.0" unitType="ms"/>
            <notes tierName="Notes">(blanket)</notes>
            <flatTier tierName="uttnum">1097</flatTier>
            <flatTier tierName="sesdat">1973-09-10</flatTier>
            <flatTier tierName="age">1;8.24</flatTier>
        </u>
        <u speaker="CHI" id="2d679491-3d15-48c4-9bdf-34ca14d0b9e9" excludeFromSearches="false">
            <orthography>
                <g>
                    <w>go</w>
                    <w>away</w>
                    <p type="PERIOD">.</p>
                </g>
            </orthography>
            <ipaTier form="model">
                <pg>
                    <w>ˈɡoʊ</w>
                    <w>əˈweɪ</w>
                    <sb>
                        <ph indexes="0" scType="SS"/>
                        <ph indexes="1" scType="UK"/>
                        <ph indexes="2" scType="UK"/>
                        <ph indexes="3" scType="UK"/>
                        <ph indexes="4" scType="WB"/>
                        <ph indexes="5" scType="UK"/>
                        <ph indexes="6" scType="SS"/>
                        <ph indexes="7" scType="UK"/>
                        <ph indexes="8" scType="UK"/>
                        <ph indexes="9" scType="UK"/>
                    </sb>
                </pg>
            </ipaTier>
            <ipaTier form="actual">
                <pg>
                    <w>ɡo</w>
                    <w>waɪ</w>
                    <sb>
                        <ph indexes="0" scType="UK"/>
                        <ph indexes="1" scType="UK"/>
                        <ph indexes="2" scType="WB"/>
                        <ph indexes="3" scType="UK"/>
                        <ph indexes="4" scType="UK"/>
                        <ph indexes="5" scType="UK"/>
                    </sb>
                </pg>
            </ipaTier>
            <alignment type="segmental">
                <ag length="0"/>
            </alignment>
            <segment startTime="0.0" duration="0.0" unitType="ms"/>
            <flatTier tierName="uttnum">1098</flatTier>
            <flatTier tierName="sesdat">1973-09-10</flatTier>
            <flatTier tierName="age">1;8.24</flatTier>
        </u>
        <u speaker="CHI" id="a4855eef-4e57-440b-84a7-34bfbc93846a" excludeFromSearches="false">
            <orthography>
                <g>
                    <w>cow</w>
                    <w>moo</w>
                    <p type="PERIOD">.</p>
                </g>
            </orthography>
            <ipaTier form="model">
                <pg>
                    <w>ˈkaʊ</w>
                    <w>muː</w>
                    <sb>
                        <ph indexes="0" scType="SS"/>
                        <ph indexes="1" scType="UK"/>
                        <ph indexes="2" scType="UK"/>
                        <ph indexes="3" scType="UK"/>
                        <ph indexes="4" scType="WB"/>
                        <ph indexes="5" scType="UK"/>
                        <ph indexes="6 7" scType="UK"/>
                    </sb>
                </pg>
            </ipaTier>
            <ipaTier form="actual">
                <pg>
                    <w>kaʊ</w>
                    <w>muː</w>
                    <sb>
                        <ph indexes="0" scType="UK"/>
                        <ph indexes="1" scType="UK"/>
                        <ph indexes="2" scType="UK"/>
                        <ph indexes="3" scType="WB"/>
                        <ph indexes="4" scType="UK"/>
                        <ph indexes="5 6" scType="UK"/>
                    </sb>
                </pg>
            </ipaTier>
            <alignment type="segmental">
                <ag length="0"/>
            </alignment>
            <segment startTime="0.0" duration="0.0" unitType="ms"/>
            <flatTier tierName="uttnum">1099</flatTier>
            <flatTier tierName="sesdat">1973-09-10</flatTier>
            <flatTier tierName="age">1;8.24</flatTier>
        </u>
        <u speaker="CHI" id="0867b922-ac48-4e1e-9529-21450b09ce3b" excludeFromSearches="false">
            <orthography>
                <g>
                    <w>shoe</w>
                    <w>on</w>
                    <p type="PERIOD">.</p>
                </g>
            </orthography>
            <ipaTier form="model">
                <pg>
                    <w>ˈʃuː</w>
                    <w>ˈɑn</w>
                    <sb>
                        <ph indexes="0" scType="SS"/>
                        <ph indexes="1" scType="UK"/>
                        <ph indexes="2 3" scType="UK"/>
                        <ph indexes="4" scType="WB"/>
                        <ph indexes="5" scType="SS"/>
                        <ph indexes="6" scType="UK"/>
                        <ph indexes="7" scType="UK"/>
                    </sb>
                </pg>
            </ipaTier>
            <ipaTier form="actual">
                <pg>
                    <w>ʃʷu</w>
                    <w>an</w>
                    <sb>
                        <ph indexes="0 1" scType="UK"/>
                        <ph indexes="2" scType="UK"/>
                        <ph indexes="3" scType="WB"/>
                        <ph indexes="4" scType="UK"/>
                        <ph indexes="5" scType="UK"/>
                    </sb>
                </pg>
            </ipaTier>
            <alignment type="segmental">
                <ag length="0"/>
            </alignment>
            <segment startTime="0.0" duration="0.0" unitType="ms"/>
            <flatTier tierName="uttnum">1100</flatTier>
            <flatTier tierName="sesdat">1973-09-10</flatTier>
            <flatTier tierName="age">1;8.24</flatTier>
        </u>
        <u speaker="CHI" id="7a312396-8992-41e8-8530-f7a0cac5a260" excludeFromSearches="false">
            <orthography>
                <g>
                    <w>drum</w>
                    <p type="PERIOD">.</p>
                </g>
            </orthography>
            <ipaTier form="model">
                <pg>
                    <w>ˈdɹʌm</w>
                    <sb>
                        <ph indexes="0" scType="SS"/>
                        <ph indexes="1" scType="UK"/>
                        <ph indexes="2" scType="UK"/>
                        <ph indexes="3" scType="UK"/>
                        <ph indexes="4" scType="UK"/>
                    </sb>
                </pg>
            </ipaTier>
            <ipaTier form="actual">
                <pg>
                    <w>dʌm</w>
                    <sb>
                        <ph indexes="0" scType="UK"/>
                        <ph indexes="1" scType="UK"/>
                        <ph indexes="2" scType="UK"/>
                    </sb>
                </pg>
            </ipaTier>
            <alignment type="segmental">
                <ag length="0"/>
            </alignment>
            <segment startTime="0.0" duration="0.0" unitType="ms"/>
            <flatTier tierName="uttnum">1101</flatTier>
            <flatTier tierName="sesdat">1973-09-10</flatTier>
            <flatTier tierName="age">1;8.24</flatTier>
        </u>
        <u speaker="CHI" id="5f9d5b2e-9909-4a6e-8a4d-9d5aa46f0b46" excludeFromSearches="false">
            <orthography>
                <g>
                    <w>pictures</w>
                    <p type="PERIOD">.</p>
                </g>
            </orthography>
            <ipaTier form="model">
                <pg>
                    <w>ˈpɪkʧəɹz</w>
                    <sb>
                        <ph indexes="0" scType="SS"/>
                        <ph indexes="1" scType="UK"/>
                        <ph indexes="2" scType="UK"/>
                        <ph indexes="3" scType="UK"/>
                        <ph indexes="4" scType="UK"/>
                        <ph indexes="5" scType="UK"/>
                        <ph indexes="6" scType="UK"/>
                        <ph indexes="7" scType="UK"/>
                    </sb>
                </pg>
            </ipaTier>
            <ipaTier form="actual">
                <pg>
                    <w>b̥iʧusʷ</w>
                    <sb>
                        <ph indexes="0 1" scType="UK"/>
                        <ph indexes="2" scType="UK"/>
                        <ph indexes="3" scType="UK"/>
                        <ph indexes="4" scType="UK"/>
                        <ph indexes="5 6" scType="UK"/>
                    </sb>
                </pg>
            </ipaTier>
            <alignment type="segmental">
                <ag length="0"/>
            </alignment>
            <segment startTime="0.0" duration="0.0" unitType="ms"/>
            <flatTier tierName="uttnum">1102</flatTier>
            <flatTier tierName="sesdat">1973-09-10</flatTier>
            <flatTier tierName="age">1;8.24</flatTier>
        </u>
        <u speaker="CHI" id="b947af6c-696f-4bf5-9793-c0e573e88e3b" excludeFromSearches="false">
            <orthography>
                <g>
                    <w>shoes</w>
                    <w>and</w>
                    <w>socks</w>
                    <p type="PERIOD">.</p>
                </g>
            </orthography>
            <ipaTier form="model">
                <pg>
                    <w>ˈʃuːz</w>
                    <w>ˈænd</w>
                    <w>ˈsɑks</w>
                    <sb>
                        <ph indexes="0" scType="SS"/>
                        <ph indexes="1" scType="UK"/>
                        <ph indexes="2 3" scType="UK"/>
                        <ph indexes="4" scType="UK"/>
                        <ph indexes="5" scType="WB"/>
                        <ph indexes="6" scType="SS"/>
                        <ph indexes="7" scType="UK"/>
                        <ph indexes="8" scType="UK"/>
                        <ph indexes="9" scType="UK"/>
                        <ph indexes="10" scType="WB"/>
                        <ph indexes="11" scType="SS"/>
                        <ph indexes="12" scType="UK"/>
                        <ph indexes="13" scType="UK"/>
                        <ph indexes="14" scType="UK"/>
                        <ph indexes="15" scType="UK"/>
                    </sb>
                </pg>
            </ipaTier>
            <ipaTier form="actual">
                <pg>
                    <w>ʃusʷ</w>
                    <w>icakç</w>
                    <sb>
                        <ph indexes="0" scType="UK"/>
                        <ph indexes="1" scType="UK"/>
                        <ph indexes="2 3" scType="UK"/>
                        <ph indexes="4" scType="WB"/>
                        <ph indexes="5" scType="UK"/>
                        <ph indexes="6" scType="UK"/>
                        <ph indexes="7" scType="UK"/>
                        <ph indexes="8" scType="UK"/>
                        <ph indexes="9" scType="UK"/>
                    </sb>
                </pg>
            </ipaTier>
            <alignment type="segmental">
                <ag length="0"/>
            </alignment>
            <segment startTime="0.0" duration="0.0" unitType="ms"/>
            <notes tierName="Notes">(imitation)</notes>
            <flatTier tierName="uttnum">1103</flatTier>
            <flatTier tierName="sesdat">1973-09-10</flatTier>
            <flatTier tierName="age">1;8.24</flatTier>
        </u>
        <u speaker="CHI" id="2e29b2c6-709c-4051-b8bd-7120acedc6de" excludeFromSearches="false">
            <orthography>
                <g>
                    <w>march</w>
                    <p type="PERIOD">.</p>
                </g>
            </orthography>
            <ipaTier form="model">
                <pg>
                    <w>ˈmɑɹʧ</w>
                    <sb>
                        <ph indexes="0" scType="SS"/>
                        <ph indexes="1" scType="UK"/>
                        <ph indexes="2" scType="UK"/>
                        <ph indexes="3" scType="UK"/>
                        <ph indexes="4" scType="UK"/>
                    </sb>
                </pg>
            </ipaTier>
            <ipaTier form="actual">
                <pg>
                    <w>maʧ</w>
                    <sb>
                        <ph indexes="0" scType="UK"/>
                        <ph indexes="1" scType="UK"/>
                        <ph indexes="2" scType="UK"/>
                    </sb>
                </pg>
            </ipaTier>
            <alignment type="segmental">
                <ag length="0"/>
            </alignment>
            <segment startTime="0.0" duration="0.0" unitType="ms"/>
            <flatTier tierName="uttnum">1104</flatTier>
            <flatTier tierName="sesdat">1973-09-10</flatTier>
            <flatTier tierName="age">1;8.24</flatTier>
        </u>
        <u speaker="CHI" id="c1b51552-d479-4de3-b592-b65edd9bf7eb" excludeFromSearches="false">
            <orthography>
                <g>
                    <w>dirty</w>
                    <p type="PERIOD">.</p>
                </g>
            </orthography>
            <ipaTier form="model">
                <pg>
                    <w>ˈdʌɹtiː</w>
                    <sb>
                        <ph indexes="0" scType="SS"/>
                        <ph indexes="1" scType="UK"/>
                        <ph indexes="2" scType="UK"/>
                        <ph indexes="3" scType="UK"/>
                        <ph indexes="4" scType="UK"/>
                        <ph indexes="5 6" scType="UK"/>
                    </sb>
                </pg>
            </ipaTier>
            <ipaTier form="actual">
                <pg>
                    <w>dʊdi</w>
                    <sb>
                        <ph indexes="0" scType="UK"/>
                        <ph indexes="1" scType="UK"/>
                        <ph indexes="2" scType="UK"/>
                        <ph indexes="3" scType="UK"/>
                    </sb>
                </pg>
            </ipaTier>
            <alignment type="segmental">
                <ag length="0"/>
            </alignment>
            <segment startTime="0.0" duration="0.0" unitType="ms"/>
            <flatTier tierName="uttnum">1105</flatTier>
            <flatTier tierName="sesdat">1973-09-10</flatTier>
            <flatTier tierName="age">1;8.24</flatTier>
        </u>
        <u speaker="CHI" id="29c01760-fee2-4296-9965-c8abb4226662" excludeFromSearches="false">
            <orthography>
                <g>
                    <w>hi</w>
                    <w>mommy</w>
                    <p type="PERIOD">.</p>
                </g>
            </orthography>
            <ipaTier form="model">
                <pg>
                    <w>ˈhaɪ</w>
                    <w>ˈmɑmiː</w>
                    <sb>
                        <ph indexes="0" scType="SS"/>
                        <ph indexes="1" scType="UK"/>
                        <ph indexes="2" scType="UK"/>
                        <ph indexes="3" scType="UK"/>
                        <ph indexes="4" scType="WB"/>
                        <ph indexes="5" scType="SS"/>
                        <ph indexes="6" scType="UK"/>
                        <ph indexes="7" scType="UK"/>
                        <ph indexes="8" scType="UK"/>
                        <ph indexes="9 10" scType="UK"/>
                    </sb>
                </pg>
            </ipaTier>
            <ipaTier form="actual">
                <pg>
                    <w>hɪ</w>
                    <w>mami</w>
                    <sb>
                        <ph indexes="0" scType="UK"/>
                        <ph indexes="1" scType="UK"/>
                        <ph indexes="2" scType="WB"/>
                        <ph indexes="3" scType="UK"/>
                        <ph indexes="4" scType="UK"/>
                        <ph indexes="5" scType="UK"/>
                        <ph indexes="6" scType="UK"/>
                    </sb>
                </pg>
            </ipaTier>
            <alignment type="segmental">
                <ag length="0"/>
            </alignment>
            <segment startTime="0.0" duration="0.0" unitType="ms"/>
            <flatTier tierName="uttnum">1106</flatTier>
            <flatTier tierName="sesdat">1973-09-10</flatTier>
            <flatTier tierName="age">1;8.24</flatTier>
        </u>
        <u speaker="CHI" id="077ffb86-19fa-403b-b636-805137284bde" excludeFromSearches="false">
            <orthography>
                <g>
                    <w>pretty</w>
                    <p type="PERIOD">.</p>
                </g>
            </orthography>
            <ipaTier form="model">
                <pg>
                    <w>ˈpɹɪtiː</w>
                    <sb>
                        <ph indexes="0" scType="SS"/>
                        <ph indexes="1" scType="UK"/>
                        <ph indexes="2" scType="UK"/>
                        <ph indexes="3" scType="UK"/>
                        <ph indexes="4" scType="UK"/>
                        <ph indexes="5 6" scType="UK"/>
                    </sb>
                </pg>
            </ipaTier>
            <ipaTier form="actual">
                <pg>
                    <w>pɪdi</w>
                    <sb>
                        <ph indexes="0" scType="UK"/>
                        <ph indexes="1" scType="UK"/>
                        <ph indexes="2" scType="UK"/>
                        <ph indexes="3" scType="UK"/>
                    </sb>
                </pg>
            </ipaTier>
            <alignment type="segmental">
                <ag length="0"/>
            </alignment>
            <segment startTime="0.0" duration="0.0" unitType="ms"/>
            <flatTier tierName="uttnum">1107</flatTier>
            <flatTier tierName="sesdat">1973-09-10</flatTier>
            <flatTier tierName="age">1;8.24</flatTier>
        </u>
        <u speaker="CHI" id="b32d50c0-4fce-4df1-bf32-a372b242bdb7" excludeFromSearches="false">
            <orthography>
                <g>
                    <w>horse</w>
                    <p type="PERIOD">.</p>
                </g>
            </orthography>
            <ipaTier form="model">
                <pg>
                    <w>ˈhɔɹs</w>
                    <sb>
                        <ph indexes="0" scType="SS"/>
                        <ph indexes="1" scType="UK"/>
                        <ph indexes="2" scType="UK"/>
                        <ph indexes="3" scType="UK"/>
                        <ph indexes="4" scType="UK"/>
                    </sb>
                </pg>
            </ipaTier>
            <ipaTier form="actual">
                <pg>
                    <w>haʊsʷ</w>
                    <sb>
                        <ph indexes="0" scType="UK"/>
                        <ph indexes="1" scType="UK"/>
                        <ph indexes="2" scType="UK"/>
                        <ph indexes="3 4" scType="UK"/>
                    </sb>
                </pg>
            </ipaTier>
            <alignment type="segmental">
                <ag length="0"/>
            </alignment>
            <segment startTime="0.0" duration="0.0" unitType="ms"/>
            <flatTier tierName="uttnum">1108</flatTier>
            <flatTier tierName="sesdat">1973-09-10</flatTier>
            <flatTier tierName="age">1;8.24</flatTier>
        </u>
        <u speaker="CHI" id="5bf498ce-6e40-4fb5-bcdc-96430ec13da1" excludeFromSearches="false">
            <orthography>
                <g>
                    <w>kitty</w>
                    <p type="PERIOD">.</p>
                </g>
            </orthography>
            <ipaTier form="model">
                <pg>
                    <w>ˈkɪtiː</w>
                    <sb>
                        <ph indexes="0" scType="SS"/>
                        <ph indexes="1" scType="UK"/>
                        <ph indexes="2" scType="UK"/>
                        <ph indexes="3" scType="UK"/>
                        <ph indexes="4 5" scType="UK"/>
                    </sb>
                </pg>
            </ipaTier>
            <ipaTier form="actual">
                <pg>
                    <w>kiki</w>
                    <sb>
                        <ph indexes="0" scType="UK"/>
                        <ph indexes="1" scType="UK"/>
                        <ph indexes="2" scType="UK"/>
                        <ph indexes="3" scType="UK"/>
                    </sb>
                </pg>
            </ipaTier>
            <alignment type="segmental">
                <ag length="0"/>
            </alignment>
            <segment startTime="0.0" duration="0.0" unitType="ms"/>
            <flatTier tierName="uttnum">1109</flatTier>
            <flatTier tierName="sesdat">1973-09-10</flatTier>
            <flatTier tierName="age">1;8.24</flatTier>
        </u>
    </transcript>
</session>
